fb_gapi/__init__.py
fb_gapi/client.py
fb_gapi/exceptions.py
fb_gapi/utils.py
facebook_messenger_sdk-0.1.0.dist-info/METADATA
facebook_messenger_sdk-0.1.0.dist-info/WHEEL
facebook_messenger_sdk-0.1.0.dist-info/top_level.txt
facebook_messenger_sdk-0.1.0.dist-info/RECORD
